clldutils/__init__.py
clldutils/apilib.py
clldutils/attrlib.py
clldutils/badge.py
clldutils/clilib.py
clldutils/color.py
clldutils/coordinates.py
clldutils/db.py
clldutils/declenum.py
clldutils/fonts.py
clldutils/html.py
clldutils/inifile.py
clldutils/iso_639_3.py
clldutils/jsonlib.py
clldutils/lgr.py
clldutils/licenses.py
clldutils/loglib.py
clldutils/markup.py
clldutils/metadata.py
clldutils/misc.py
clldutils/oaipmh.py
clldutils/paginate.py
clldutils/path.py
clldutils/sfm.py
clldutils/source.py
clldutils/svg.py
clldutils/text.py
clldutils/ziparchive.py
clldutils/fonts/CharisSIL-Bold.ttf
clldutils/fonts/CharisSIL-BoldItalic.ttf
clldutils/fonts/CharisSIL-Italic.ttf
clldutils/fonts/CharisSIL-Regular.ttf
clldutils/fonts/OFL.txt
clldutils/legalcode/AGPL-3.0
clldutils/legalcode/Apache-2.0
clldutils/legalcode/BSD-2-Clause
clldutils/legalcode/BSD-3-Clause
clldutils/legalcode/CC-BY-3.0
clldutils/legalcode/CC-BY-4.0
clldutils/legalcode/CC-BY-NC-3.0
clldutils/legalcode/CC-BY-NC-4.0
clldutils/legalcode/CC-BY-NC-ND-3.0
clldutils/legalcode/CC-BY-NC-ND-4.0
clldutils/legalcode/CC-BY-NC-SA-3.0
clldutils/legalcode/CC-BY-NC-SA-4.0
clldutils/legalcode/CC-BY-ND-3.0
clldutils/legalcode/CC-BY-ND-4.0
clldutils/legalcode/CC-BY-SA-3.0
clldutils/legalcode/CC-BY-SA-4.0
clldutils/legalcode/GPL-2.0
clldutils/legalcode/GPL-3.0
clldutils/legalcode/LGPL-2.1
clldutils/legalcode/LGPL-3.0
clldutils/legalcode/MIT
clldutils/legalcode/MPL-2.0
clldutils/legalcode/Unlicense
clldutils-3.24.2.dist-info/LICENSE
clldutils-3.24.2.dist-info/METADATA
clldutils-3.24.2.dist-info/WHEEL
clldutils-3.24.2.dist-info/top_level.txt
clldutils-3.24.2.dist-info/RECORD
